README.md
setup.cfg
setup.py
tensorflow_plot.egg-info/PKG-INFO
tensorflow_plot.egg-info/SOURCES.txt
tensorflow_plot.egg-info/dependency_links.txt
tensorflow_plot.egg-info/not-zip-safe
tensorflow_plot.egg-info/requires.txt
tensorflow_plot.egg-info/top_level.txt
tfplot/__init__.py
tfplot/contrib.py
tfplot/contrib_test.py
tfplot/figure.py
tfplot/mpl_figure.py
tfplot/ops.py
tfplot/ops_test.py
tfplot/summary.py
tfplot/summary_test.py
tfplot/test_util.py
tfplot/util.py
tfplot/wrapper.py
tfplot/wrapper_test.py