Metadata-Version: 2.1
Name: tensorflow-plot
Version: 0.3.1
Summary: TensorFlow Plot
Home-page: https://github.com/wookayin/tensorflow-plot
Author: Jongwook Choi
Author-email: wookayin@gmail.com
License: MIT License
Keywords: tensorflow matplotlib tensorboard plot tfplot
Platform: UNKNOWN
Classifier: Development Status :: 3 - Alpha
Classifier: License :: OSI Approved :: MIT License
Classifier: Programming Language :: Python :: 2.7
Classifier: Programming Language :: Python :: 3
